peakrdl/__about__.py
peakrdl/__init__.py
peakrdl/__main__.py
peakrdl/importer.py
peakrdl/main.py
peakrdl/process_input.py
peakrdl/py.typed
peakrdl/subcommand.py
peakrdl/cmd/__init__.py
peakrdl/cmd/dump.py
peakrdl/cmd/list_globals.py
peakrdl/cmd/preprocess.py
peakrdl/config/__init__.py
peakrdl/config/loader.py
peakrdl/config/schema.py
peakrdl/plugins/__init__.py
peakrdl/plugins/entry_points.py
peakrdl/plugins/exporter.py
peakrdl/plugins/importer.py
peakrdl_cli-1.3.0.dist-info/licenses/LICENSE
peakrdl_cli-1.3.0.dist-info/METADATA
peakrdl_cli-1.3.0.dist-info/WHEEL
peakrdl_cli-1.3.0.dist-info/entry_points.txt
peakrdl_cli-1.3.0.dist-info/top_level.txt
peakrdl_cli-1.3.0.dist-info/RECORD
